tunablex/__init__.py
tunablex/cli.py
tunablex/cli_helpers.py
tunablex/context.py
tunablex/decorators.py
tunablex/io.py
tunablex/naming.py
tunablex/registry.py
tunablex/runtime.py
tunablex-0.1.5.dist-info/METADATA
tunablex-0.1.5.dist-info/WHEEL
tunablex-0.1.5.dist-info/licenses/LICENSE
tunablex-0.1.5.dist-info/RECORD
