Metadata-Version: 2.4
Name: tunablex
Version: 0.1.5
Summary: Function-first tunables with auto JSON/YAML/TOML config & schema, per-executable composition (tags or trace), and runtime auto-injection.
Project-URL: Homepage, https://github.com/jackpap/tunableX
Project-URL: Issues, https://github.com/jackpap/tunableX/issues
Author: Jacques Papper
Author-email: Vincent Drouet <v.drouet@iconcfd.com>
License: MIT
License-File: LICENSE
Classifier: Development Status :: 3 - Alpha
Classifier: License :: OSI Approved :: MIT License
Classifier: Programming Language :: Python :: 3
Classifier: Programming Language :: Python :: 3 :: Only
Classifier: Programming Language :: Python :: 3.10
Classifier: Programming Language :: Python :: 3.11
Classifier: Programming Language :: Python :: 3.12
Classifier: Typing :: Typed
Requires-Python: >=3.10
Requires-Dist: pydantic>=2.4
Provides-Extra: all
Requires-Dist: jsonargparse>=4.26; extra == 'all'
Requires-Dist: pyyaml>=6.0.1; extra == 'all'
Provides-Extra: dev
Requires-Dist: jsonargparse>=4.26; extra == 'dev'
Requires-Dist: pre-commit>=3.5.0; extra == 'dev'
Requires-Dist: pytest>=8.0.0; extra == 'dev'
Requires-Dist: pyyaml>=6.0.1; extra == 'dev'
Requires-Dist: ruff>=0.6.0; extra == 'dev'
Provides-Extra: jsonargparse
Requires-Dist: jsonargparse>=4.26; extra == 'jsonargparse'
Provides-Extra: yaml
Requires-Dist: pyyaml>=6.0.1; extra == 'yaml'
